calculadora_varanda/main.py
calculadora_varanda-0.0.1.dist-info/WHEEL
calculadora_varanda-0.0.1.dist-info/METADATA
calculadora_varanda-0.0.1.dist-info/RECORD
