Metadata-Version: 2.1
Name: calculadora-varanda
Version: 0.0.1
Summary: Está é uma calculadora mantida pela Codaqui.
License: MIT
Author: Pedro Varanda
Requires-Python: >=3.8,<4.0
Classifier: License :: OSI Approved :: MIT License
Classifier: Programming Language :: Python :: 3
Classifier: Programming Language :: Python :: 3.8
Classifier: Programming Language :: Python :: 3.9
